setup.py
gapy/__init__.py
gapy/client.py
gapy/error.py
gapy/response.py
gapy.egg-info/PKG-INFO
gapy.egg-info/SOURCES.txt
gapy.egg-info/dependency_links.txt
gapy.egg-info/requires.txt
gapy.egg-info/top_level.txt