Metadata-Version: 1.1
Name: gapy
Version: 1.3.4
Summary: Painless Google Analytics
Home-page: https://github.com/alphagov/gapy
Author: Rob Young
Author-email: rob@roryoung.co.uk
License: https://raw.github.com/alphagov/gapy/master/LICENSE
Platform: UNKNOWN
Classifier: Development Status :: 3 - Alpha
Classifier: Intended Audience :: Developers
Classifier: Natural Language :: English
Classifier: Programming Language :: Python
Classifier: License :: OSI Approved :: MIT License
